anoexpress/__init__.py
anoexpress/candidates.py
anoexpress/data.py
anoexpress/gsea.py
anoexpress/plot.py
anoexpress/utils.py
anoexpress-0.3.2.dist-info/LICENSE
anoexpress-0.3.2.dist-info/METADATA
anoexpress-0.3.2.dist-info/WHEEL
anoexpress-0.3.2.dist-info/RECORD
