Metadata-Version: 2.3
Name: anoexpress
Version: 0.3.2
Summary: A package to access insecticide resistance gene expression meta analyse in Anopheles mosquitoes
License: MIT
Author: Sanjay Nagi
Author-email: sanjay.nagi@lstmed.ac.uk
Requires-Python: >=3.10,<3.13
Classifier: License :: OSI Approved :: MIT License
Classifier: Programming Language :: Python :: 3
Classifier: Programming Language :: Python :: 3.10
Classifier: Programming Language :: Python :: 3.11
Classifier: Programming Language :: Python :: 3.12
Requires-Dist: bokeh
Requires-Dist: ipykernel
Requires-Dist: malariagen_data (>13.0.1)
Requires-Dist: numpy
Requires-Dist: pandas
Requires-Dist: papermill
Requires-Dist: plotly (>=5.12.0,<6.0.0)
Requires-Dist: scikit-allel
Requires-Dist: scipy
Requires-Dist: seaborn
Requires-Dist: statsmodels
Requires-Dist: tqdm
Project-URL: Documentation, https://sanjaynagi.github.io/AnoExpress/
Project-URL: Repository, https://github.com/sanjaynagi/AnoExpress
